lamana/__init__.py
lamana/constructs.py
lamana/distributions.py
lamana/input_.py
lamana/lt_exceptions.py
lamana/output_.py
lamana/theories.py
lamana/models/Wilson_LT.py
lamana/models/__init__.py
lamana/models/fixtures/__init__.py
lamana/models/fixtures/fixture_model_class.py
lamana/models/fixtures/fixture_model_func.py
lamana/models/fixtures/fixture_model_module_a.py
lamana/models/fixtures/fixture_model_module_b.py
lamana/tests/__init__.py
lamana/tests/_test_example.py
lamana/tests/test_constructs.py
lamana/tests/test_controls.py
lamana/tests/test_distributions.py
lamana/tests/test_input_.py
lamana/tests/test_output_.py
lamana/tests/test_plottools.py
lamana/tests/test_theories.py
lamana/tests/test_utils.py
lamana/tests/controls_LT/laminate_5ply_p5_t2.0_100-100-1600.csv
lamana/tests/controls_LT/laminate_5ply_p5_t2.0_100-200-1400.csv
lamana/tests/controls_LT/laminate_5ply_p5_t2.0_200-100-1400.csv
lamana/tests/controls_LT/laminate_5ply_p5_t2.0_200-200-1200.csv
lamana/tests/controls_LT/laminate_5ply_p5_t2.0_350-400-500.csv
lamana/tests/controls_LT/laminate_5ply_p5_t2.0_400-200-800.csv
"lamana/tests/controls_LT/w_laminate_10ply_p1_t1.4_500.0-[50.0,50.0,50.0,50.0]-0.0.csv"
"lamana/tests/controls_LT/w_laminate_10ply_p2_t1.4_500.0-[50.0,50.0,50.0,50.0]-0.0.csv"
"lamana/tests/controls_LT/w_laminate_10ply_p3_t1.4_500.0-[50.0,50.0,50.0,50.0]-0.0.csv"
"lamana/tests/controls_LT/w_laminate_10ply_p4_t1.4_500.0-[50.0,50.0,50.0,50.0]-0.0.csv"
"lamana/tests/controls_LT/w_laminate_10ply_p5_t1.4_500.0-[50.0,50.0,50.0,50.0]-0.0.csv"
"lamana/tests/controls_LT/w_laminate_10ply_p7_t1.4_500.0-[50.0,50.0,50.0,50.0]-0.0.csv"
"lamana/tests/controls_LT/w_laminate_10ply_p9_t1.4_500.0-[50.0,50.0,50.0,50.0]-0.0.csv"
lamana/tests/controls_LT/w_laminate_1ply_p1_t2.0_0.0-[0.0]-2000.0.csv
lamana/tests/controls_LT/w_laminate_1ply_p2_t2.0_0.0-[0.0]-2000.0.csv
lamana/tests/controls_LT/w_laminate_1ply_p3_t2.0_0.0-[0.0]-2000.0.csv
lamana-0.4.12.dist-info/DESCRIPTION.rst
lamana-0.4.12.dist-info/METADATA
lamana-0.4.12.dist-info/RECORD
lamana-0.4.12.dist-info/WHEEL
lamana-0.4.12.dist-info/metadata.json
lamana-0.4.12.dist-info/top_level.txt
