Metadata-Version: 2.0
Name: lamana
Version: 0.4.12
Summary: An extensible Python package for laminate analysis
Home-page: https://github.com/par2/lamana
Author: P. Robinson II
Author-email: par2.get@gmail.com
License: BSD
Download-URL: https://github.com/par2/lamana/tarball/0.4.12
Keywords: laminate analysis,visualization
Platform: UNKNOWN
Classifier: Framework :: IPython
Classifier: Intended Audience :: Science/Research
Classifier: License :: OSI Approved :: BSD License
Classifier: Operating System :: OS Independent
Classifier: Programming Language :: Python
Classifier: Topic :: Scientific/Engineering
Requires-Dist: matplotlib
Requires-Dist: numpy
Requires-Dist: openpyxl
Requires-Dist: pandas
Requires-Dist: six
